ipmisim/__init__.py
ipmisim/fakebmc.py
ipmisim/fakesession.py
ipmisim/ipmisim.py
ipmisim-0.8.dist-info/LICENSE
ipmisim-0.8.dist-info/METADATA
ipmisim-0.8.dist-info/WHEEL
ipmisim-0.8.dist-info/entry_points.txt
ipmisim-0.8.dist-info/top_level.txt
ipmisim-0.8.dist-info/RECORD
