Metadata-Version: 2.1
Name: ipmisim
Version: 0.8
Summary: ipmisim is a fake ipmi server
Home-page: https://github.com/rhtyd/ipmisim
Maintainer: Rohit Yadav
Maintainer-email: rohit@apache.org
License: ASL 2.0
Platform: Any
Classifier: Development Status :: 4 - Beta
Classifier: Environment :: Console
Classifier: Intended Audience :: Developers
Classifier: Intended Audience :: End Users/Desktop
Classifier: Operating System :: POSIX :: Linux
Classifier: Programming Language :: Python
Classifier: Topic :: Software Development :: Testing
Classifier: Topic :: Utilities
Requires-Dist: pyghmi (==1.2.16)
